{"actor":{"user":{"data":{},"ID":0,"caps":[],"cap_key":null,"roles":[],"allcaps":[],"filter":null},"device":"PC"},"verb":{"id":"select","display":{"en-US":"select"}},"object":[{"postItem":{"postId":1124,"postDate":"2022-01-07 19:02","postTitle":"[uc2a4ub204ub9c1ucee4] uc90c-ud074ub85cubc14 ubcc0ud658 ubc0f uc81cucd9c ubc29ubc95","postContent":"<p>uc548ub155ud558uc138uc694,</p>n<p>uc2a4ub204ub85cuc5d0 ucc38uc5ecud558uace0 uacc4uc2e0 uc2a4ub204ub9c1ucee4 uc5ecub7ecubd84ub4e4uc774 ud65cuc6a9ud560 uc218 uc788ub294 uc90c-ud074ub85cubc14 uc5f0ub3d9ubc95uc744 uc54cub824ub4dcub9acuaca0uc2b5ub2c8ub2e4.</p>n<p> </p>n<h1>step 1. uc90cuacfc ud074ub85cubc14ub97c uc5f0uacb0ud558uae30</h1>n<p>n<img loading="lazy" class="alignnone size-full wp-image-1189" src="http://snuro.easypress.me/wp-content/uploads/2022/01/zoom1.png" alt="" width="1230" height="644" srcset="https://snuro.easypress.me/wp-content/uploads/2022/01/zoom1.png 1230w, https://snuro.easypress.me/wp-content/uploads/2022/01/zoom1-300x157.png 300w, https://snuro.easypress.me/wp-content/uploads/2022/01/zoom1-1024x536.png 1024w, https://snuro.easypress.me/wp-content/uploads/2022/01/zoom1-768x402.png 768w" sizes="(max-width: 1230px) 100vw, 1230px" /></p>n<ol>n<li>ub124uc774ubc84 ud074ub85cubc14 PC ud654uba74uc5d0uc11c</li>n<li>uc124uc815 u2192 uc11cube44uc2a4 uc5f0uacb0uc5d0uc11c uc90cuc744 uc5f0uacb0ud574uc90dub2c8ub2e4.</li>n</ol>n<p>n<a href="https://blog.naver.com/PostView.naver?blogId=clova_ai&logNo=222365799633&redirect=Dlog&widgetTypeCall=true&directAccess=false">[ud074ub85cubc14ub178ud2b8] uc774ub807uac8c ud65cuc6a9ud558uc138uc694 – uc90c uc5f0ub3d9ud574uc11c ub178ud2b8 ub9ccub4e4uae30</a></p>n<p> </p>n<p> </p>n<h1>step 2. uba58ud1a0ub9c1 uc9c4ud589</h1>n</p>n<h1><img loading="lazy" class="alignnone size-full wp-image-1188" style="color: var(--global--color-primary); font-family: var(--global--font-secondary); font-size: var(--global--font-size-base);" src="http://snuro.easypress.me/wp-content/uploads/2022/01/zoom2.png" alt="" width="1046" height="276" srcset="https://snuro.easypress.me/wp-content/uploads/2022/01/zoom2.png 1046w, https://snuro.easypress.me/wp-content/uploads/2022/01/zoom2-300x79.png 300w, https://snuro.easypress.me/wp-content/uploads/2022/01/zoom2-1024x270.png 1024w, https://snuro.easypress.me/wp-content/uploads/2022/01/zoom2-768x203.png 768w" sizes="(max-width: 1046px) 100vw, 1046px" /></h1>n</p>n<ol>n<li>uc90cuacfc ub124uc774ubc84 ud074ub85cubc14ub97c uc5f0uacb0ud55c ub4a4uc5d0, uc90c ud68cuc758ub97c uc2dcuc791ud574ubd05ub2c8ub2e4.</li>n<li>uc790ub3d9uc73cub85c <strong>ud654uba74 ub179ud654</strong>uc640 <strong>ub124uc774ubc84 ud074ub85cubc14 ub77cuc774ube0c uc2a4ud2b8ub9acubc0d</strong>uc774 uc9c4ud589ub429ub2c8ub2e4.</li>n</ol>n<p>n </p>n<p> </p>n<h1>step 3. ub4dcub86dubc15uc2a4uc5d0 uc81cucd9c ud83dudca5uc911uc694ud83dudca5</h1>n<p>nuba58ud1a0ub9c1uc744 uc885ub8ccud558uba74, ub450 uac00uc9c0 ud30cuc77cuc774 uc0dduc131ub429ub2c8ub2e4. ub450 ud30cuc77cuc744 uc218uc815ud55c ub4a4uc5d0 ub4dcub86dubc15uc2a4 ub9c1ud06cub97c ud1b5ud574 uc81cucd9cud569ub2c8ub2e4.</p>n<h3><img loading="lazy" class="alignnone size-full wp-image-1187" style="color: var(--global--color-primary); font-family: var(--global--font-secondary); font-size: var(--global--font-size-base);" src="http://snuro.easypress.me/wp-content/uploads/2022/01/zoom3.png" alt="" width="1226" height="915" srcset="https://snuro.easypress.me/wp-content/uploads/2022/01/zoom3.png 1226w, https://snuro.easypress.me/wp-content/uploads/2022/01/zoom3-300x224.png 300w, https://snuro.easypress.me/wp-content/uploads/2022/01/zoom3-1024x764.png 1024w, https://snuro.easypress.me/wp-content/uploads/2022/01/zoom3-768x573.png 768w" sizes="(max-width: 1226px) 100vw, 1226px" /></h3>n</p>n<ol>n<li>ucc38uac00uc790 uc774ub984 uae30uc785ucc38uc11duc790 uc774ub984uc744 {uba58ud1a0 + uc22buc790}, {uba58ud2f0 + uc22buc790}<strong>uc73cub85c uc218uc815ud574uc90dub2c8ub2e4.</strong>ex) uba58ud1a0 3uba85, uba58ud2f0 2uba85uc778 uacbduc6b0,n<p>ucc38uc11duc7901 u2192 uba58ud1a01, ucc38uac00uc7902 u2192 uba58ud1a02, ucc38uac00uc7903 u2192 uba58ud2f01, ucc38uac00uc7904 u2192 uba58ud2f02, ucc38uac00uc7905 u2192 uba58ud1a03</li>n</p>n<li>ub2e4ub978 uc774ub984uc73cub85c uc800uc7a5uc2dcuac04 uae30ub85duc774 ud3ecud568ub41c ud30cuc77cuc744 <strong>{Nuc8fcucc28_uba58ud1a0uc774ub984}.txt</strong> uc73cub85c uc800uc7a5ud574uc90dub2c8ub2e4ex) 1uc8fcucc28_ubc15uc124ub791.txt</li>n</ol>n<p>n </p>n<h3>ub4dcub86dubc15uc2a4uc5d0 uc81cucd9c (<a href="https://www.dropbox.com/request/DDfkyuncOthwFBlyDW3x">uc81cucd9cub9c1ud06c</a>)</h3>n","postContentClear":"uc548ub155ud558uc138uc694,rnrnuc2a4ub204ub85cuc5d0 ucc38uc5ecud558uace0 uacc4uc2e0 uc2a4ub204ub9c1ucee4 uc5ecub7ecubd84ub4e4uc774 ud65cuc6a9ud560 uc218 uc788ub294 uc90c-ud074ub85cubc14 uc5f0ub3d9ubc95uc744 uc54cub824ub4dcub9acuaca0uc2b5ub2c8ub2e4.rnrn rn<h1>step 1. uc90cuacfc ud074ub85cubc14ub97c uc5f0uacb0ud558uae30</h1>rn<img class="alignnone size-full wp-image-1189" src="http://snuro.easypress.me/wp-content/uploads/2022/01/zoom1.png" alt="" width="1230" height="644" />rn<ol>rn t<li>ub124uc774ubc84 ud074ub85cubc14 PC ud654uba74uc5d0uc11c</li>rn t<li>uc124uc815 u2192 uc11cube44uc2a4 uc5f0uacb0uc5d0uc11c uc90cuc744 uc5f0uacb0ud574uc90dub2c8ub2e4.</li>rn</ol>rn<a href="https://blog.naver.com/PostView.naver?blogId=clova_ai&logNo=222365799633&redirect=Dlog&widgetTypeCall=true&directAccess=false">[ud074ub85cubc14ub178ud2b8] uc774ub807uac8c ud65cuc6a9ud558uc138uc694 - uc90c uc5f0ub3d9ud574uc11c ub178ud2b8 ub9ccub4e4uae30</a>rnrn rnrn rn<h1>step 2. uba58ud1a0ub9c1 uc9c4ud589</h1>rn<h1><img class="alignnone size-full wp-image-1188" style="color: var(--global--color-primary); font-family: var(--global--font-secondary); font-size: var(--global--font-size-base);" src="http://snuro.easypress.me/wp-content/uploads/2022/01/zoom2.png" alt="" width="1046" height="276" /></h1>rn<ol>rn t<li>uc90cuacfc ub124uc774ubc84 ud074ub85cubc14ub97c uc5f0uacb0ud55c ub4a4uc5d0, uc90c ud68cuc758ub97c uc2dcuc791ud574ubd05ub2c8ub2e4.</li>rn t<li>uc790ub3d9uc73cub85c <strong>ud654uba74 ub179ud654</strong>uc640 <strong>ub124uc774ubc84 ud074ub85cubc14 ub77cuc774ube0c uc2a4ud2b8ub9acubc0d</strong>uc774 uc9c4ud589ub429ub2c8ub2e4.</li>rn</ol>rn rnrn rn<h1>step 3. ub4dcub86dubc15uc2a4uc5d0 uc81cucd9c ud83dudca5uc911uc694ud83dudca5</h1>rnuba58ud1a0ub9c1uc744 uc885ub8ccud558uba74, ub450 uac00uc9c0 ud30cuc77cuc774 uc0dduc131ub429ub2c8ub2e4. ub450 ud30cuc77cuc744 uc218uc815ud55c ub4a4uc5d0 ub4dcub86dubc15uc2a4 ub9c1ud06cub97c ud1b5ud574 uc81cucd9cud569ub2c8ub2e4.rn<h3><img class="alignnone size-full wp-image-1187" style="color: var(--global--color-primary); font-family: var(--global--font-secondary); font-size: var(--global--font-size-base);" src="http://snuro.easypress.me/wp-content/uploads/2022/01/zoom3.png" alt="" width="1226" height="915" /></h3>rn<ol>rn t<li>ucc38uac00uc790 uc774ub984 uae30uc785ucc38uc11duc790 uc774ub984uc744 {uba58ud1a0 + uc22buc790}, {uba58ud2f0 + uc22buc790}<strong>uc73cub85c uc218uc815ud574uc90dub2c8ub2e4.</strong>ex) uba58ud1a0 3uba85, uba58ud2f0 2uba85uc778 uacbduc6b0,rnrnucc38uc11duc7901 u2192 uba58ud1a01, ucc38uac00uc7902 u2192 uba58ud1a02, ucc38uac00uc7903 u2192 uba58ud2f01, ucc38uac00uc7904 u2192 uba58ud2f02, ucc38uac00uc7905 u2192 uba58ud1a03</li>rn t<li>ub2e4ub978 uc774ub984uc73cub85c uc800uc7a5uc2dcuac04 uae30ub85duc774 ud3ecud568ub41c ud30cuc77cuc744 <strong>{Nuc8fcucc28_uba58ud1a0uc774ub984}.txt</strong> uc73cub85c uc800uc7a5ud574uc90dub2c8ub2e4ex) 1uc8fcucc28_ubc15uc124ub791.txt</li>rn</ol>rn rn<h3>ub4dcub86dubc15uc2a4uc5d0 uc81cucd9c (<a href="https://www.dropbox.com/request/DDfkyuncOthwFBlyDW3x">uc81cucd9cub9c1ud06c</a>)</h3>","postTags":[""],"postAuthorName":"*","postAuthorImage":"","postAuthorId":"42","postAuthorRole":"uc77cubc18ud68cuc6d0","prevPost":1125,"nextPost":1084,"commentsCount":"0","viewsCount":"10","postFiles":0,"thumbnail":false,"postExtra":0,"pdf":0,"ip":"52.79.92.211"}},{"viewTime":1641621086362}]}